[
  {
    "pos": 0,
    "label": "stab",
    "start": 60,
    "end": 66,
    "diff": 66,
    "stab": 1,
    "swing": 0,
    "total": 1,
    "stab_pct": 1.0,
    "swing_pct": 0.0
  },
  {
    "pos": 1,
    "label": "swing",
    "start": 103,
    "end": 109,
    "diff": 43,
    "stab": 1,
    "swing": 1,
    "total": 2,
    "stab_pct": 0.5,
    "swing_pct": 0.5
  },
  {
    "pos": 2,
    "label": "swing",
    "start": 146,
    "end": 153,
    "diff": 43,
    "stab": 1,
    "swing": 2,
    "total": 3,
    "stab_pct": 0.333,
    "swing_pct": 0.667
  },
  {
    "pos": 3,
    "label": "swing",
    "start": 190,
    "end": 197,
    "diff": 44,
    "stab": 1,
    "swing": 3,
    "total": 4,
    "stab_pct": 0.25,
    "swing_pct": 0.75
  },
  {
    "pos": 4,
    "label": "swing",
    "start": 232,
    "end": 240,
    "diff": 42,
    "stab": 1,
    "swing": 4,
    "total": 5,
    "stab_pct": 0.2,
    "swing_pct": 0.8
  },
  {
    "pos": 5,
    "label": "swing",
    "start": 277,
    "end": 284,
    "diff": 45,
    "stab": 1,
    "swing": 5,
    "total": 6,
    "stab_pct": 0.167,
    "swing_pct": 0.833
  },
  {
    "pos": 6,
    "label": "stab",
    "start": 317,
    "end": 322,
    "diff": 40,
    "stab": 2,
    "swing": 5,
    "total": 7,
    "stab_pct": 0.286,
    "swing_pct": 0.714
  },
  {
    "pos": 7,
    "label": "stab",
    "start": 356,
    "end": 362,
    "diff": 39,
    "stab": 3,
    "swing": 5,
    "total": 8,
    "stab_pct": 0.375,
    "swing_pct": 0.625
  },
  {
    "pos": 8,
    "label": "swing",
    "start": 400,
    "end": 406,
    "diff": 44,
    "stab": 3,
    "swing": 6,
    "total": 9,
    "stab_pct": 0.333,
    "swing_pct": 0.667
  },
  {
    "pos": 9,
    "label": "swing",
    "start": 443,
    "end": 448,
    "diff": 43,
    "stab": 3,
    "swing": 7,
    "total": 10,
    "stab_pct": 0.3,
    "swing_pct": 0.7
  },
  {
    "pos": 10,
    "label": "stab",
    "start": 483,
    "end": 488,
    "diff": 40,
    "stab": 4,
    "swing": 7,
    "total": 11,
    "stab_pct": 0.364,
    "swing_pct": 0.636
  },
  {
    "pos": 11,
    "label": "swing",
    "start": 526,
    "end": 531,
    "diff": 43,
    "stab": 4,
    "swing": 8,
    "total": 12,
    "stab_pct": 0.333,
    "swing_pct": 0.667
  },
  {
    "pos": 12,
    "label": "swing",
    "start": 569,
    "end": 573,
    "diff": 43,
    "stab": 4,
    "swing": 9,
    "total": 13,
    "stab_pct": 0.308,
    "swing_pct": 0.692
  },
  {
    "pos": 13,
    "label": "swing",
    "start": 612,
    "end": 617,
    "diff": 43,
    "stab": 4,
    "swing": 10,
    "total": 14,
    "stab_pct": 0.286,
    "swing_pct": 0.714
  },
  {
    "pos": 14,
    "label": "swing",
    "start": 655,
    "end": 662,
    "diff": 43,
    "stab": 4,
    "swing": 11,
    "total": 15,
    "stab_pct": 0.267,
    "swing_pct": 0.733
  },
  {
    "pos": 15,
    "label": "swing",
    "start": 698,
    "end": 704,
    "diff": 43,
    "stab": 4,
    "swing": 12,
    "total": 16,
    "stab_pct": 0.25,
    "swing_pct": 0.75
  },
  {
    "pos": 16,
    "label": "stab",
    "start": 738,
    "end": 742,
    "diff": 40,
    "stab": 5,
    "swing": 12,
    "total": 17,
    "stab_pct": 0.294,
    "swing_pct": 0.706
  },
  {
    "pos": 17,
    "label": "swing",
    "start": 781,
    "end": 786,
    "diff": 43,
    "stab": 5,
    "swing": 13,
    "total": 18,
    "stab_pct": 0.278,
    "swing_pct": 0.722
  },
  {
    "pos": 18,
    "label": "stab",
    "start": 821,
    "end": 825,
    "diff": 40,
    "stab": 6,
    "swing": 13,
    "total": 19,
    "stab_pct": 0.316,
    "swing_pct": 0.684
  },
  {
    "pos": 19,
    "label": "swing",
    "start": 866,
    "end": 871,
    "diff": 45,
    "stab": 6,
    "swing": 14,
    "total": 20,
    "stab_pct": 0.3,
    "swing_pct": 0.7
  },
  {
    "pos": 20,
    "label": "swing",
    "start": 909,
    "end": 915,
    "diff": 43,
    "stab": 6,
    "swing": 15,
    "total": 21,
    "stab_pct": 0.286,
    "swing_pct": 0.714
  },
  {
    "pos": 21,
    "label": "stab",
    "start": 949,
    "end": 954,
    "diff": 40,
    "stab": 7,
    "swing": 15,
    "total": 22,
    "stab_pct": 0.318,
    "swing_pct": 0.682
  },
  {
    "pos": 22,
    "label": "swing",
    "start": 994,
    "end": 1000,
    "diff": 45,
    "stab": 7,
    "swing": 16,
    "total": 23,
    "stab_pct": 0.304,
    "swing_pct": 0.696
  },
  {
    "pos": 23,
    "label": "swing",
    "start": 1037,
    "end": 1043,
    "diff": 43,
    "stab": 7,
    "swing": 17,
    "total": 24,
    "stab_pct": 0.292,
    "swing_pct": 0.708
  },
  {
    "pos": 24,
    "label": "swing",
    "start": 1080,
    "end": 1085,
    "diff": 43,
    "stab": 7,
    "swing": 18,
    "total": 25,
    "stab_pct": 0.28,
    "swing_pct": 0.72
  },
  {
    "pos": 25,
    "label": "stab",
    "start": 1120,
    "end": 1124,
    "diff": 40,
    "stab": 8,
    "swing": 18,
    "total": 26,
    "stab_pct": 0.308,
    "swing_pct": 0.692
  },
  {
    "pos": 26,
    "label": "swing",
    "start": 1163,
    "end": 1169,
    "diff": 43,
    "stab": 8,
    "swing": 19,
    "total": 27,
    "stab_pct": 0.296,
    "swing_pct": 0.704
  },
  {
    "pos": 27,
    "label": "stab",
    "start": 1202,
    "end": 1207,
    "diff": 39,
    "stab": 9,
    "swing": 19,
    "total": 28,
    "stab_pct": 0.321,
    "swing_pct": 0.679
  },
  {
    "pos": 28,
    "label": "stab",
    "start": 1244,
    "end": 1249,
    "diff": 42,
    "stab": 10,
    "swing": 19,
    "total": 29,
    "stab_pct": 0.345,
    "swing_pct": 0.655
  },
  {
    "pos": 29,
    "label": "swing",
    "start": 1289,
    "end": 1295,
    "diff": 45,
    "stab": 10,
    "swing": 20,
    "total": 30,
    "stab_pct": 0.333,
    "swing_pct": 0.667
  },
  {
    "pos": 30,
    "label": "swing",
    "start": 1332,
    "end": 1338,
    "diff": 43,
    "stab": 10,
    "swing": 21,
    "total": 31,
    "stab_pct": 0.323,
    "swing_pct": 0.677
  },
  {
    "pos": 31,
    "label": "stab",
    "start": 1372,
    "end": 1377,
    "diff": 40,
    "stab": 11,
    "swing": 21,
    "total": 32,
    "stab_pct": 0.344,
    "swing_pct": 0.656
  },
  {
    "pos": 32,
    "label": "swing",
    "start": 1415,
    "end": 1421,
    "diff": 43,
    "stab": 11,
    "swing": 22,
    "total": 33,
    "stab_pct": 0.333,
    "swing_pct": 0.667
  },
  {
    "pos": 33,
    "label": "swing",
    "start": 1459,
    "end": 1465,
    "diff": 44,
    "stab": 11,
    "swing": 23,
    "total": 34,
    "stab_pct": 0.324,
    "swing_pct": 0.676
  },
  {
    "pos": 34,
    "label": "swing",
    "start": 1502,
    "end": 1508,
    "diff": 43,
    "stab": 11,
    "swing": 24,
    "total": 35,
    "stab_pct": 0.314,
    "swing_pct": 0.686
  },
  {
    "pos": 35,
    "label": "swing",
    "start": 1545,
    "end": 1551,
    "diff": 43,
    "stab": 11,
    "swing": 25,
    "total": 36,
    "stab_pct": 0.306,
    "swing_pct": 0.694
  },
  {
    "pos": 36,
    "label": "stab",
    "start": 1585,
    "end": 1590,
    "diff": 40,
    "stab": 12,
    "swing": 25,
    "total": 37,
    "stab_pct": 0.324,
    "swing_pct": 0.676
  },
  {
    "pos": 37,
    "label": "swing",
    "start": 1627,
    "end": 1632,
    "diff": 42,
    "stab": 12,
    "swing": 26,
    "total": 38,
    "stab_pct": 0.316,
    "swing_pct": 0.684
  },
  {
    "pos": 38,
    "label": "swing",
    "start": 1670,
    "end": 1676,
    "diff": 43,
    "stab": 12,
    "swing": 27,
    "total": 39,
    "stab_pct": 0.308,
    "swing_pct": 0.692
  },
  {
    "pos": 39,
    "label": "stab",
    "start": 1710,
    "end": 1715,
    "diff": 40,
    "stab": 13,
    "swing": 27,
    "total": 40,
    "stab_pct": 0.325,
    "swing_pct": 0.675
  },
  {
    "pos": 40,
    "label": "stab",
    "start": 1752,
    "end": 1757,
    "diff": 42,
    "stab": 14,
    "swing": 27,
    "total": 41,
    "stab_pct": 0.341,
    "swing_pct": 0.659
  },
  {
    "pos": 41,
    "label": "swing",
    "start": 1795,
    "end": 1801,
    "diff": 43,
    "stab": 14,
    "swing": 28,
    "total": 42,
    "stab_pct": 0.333,
    "swing_pct": 0.667
  },
  {
    "pos": 42,
    "label": "stab",
    "start": 1835,
    "end": 1840,
    "diff": 40,
    "stab": 15,
    "swing": 28,
    "total": 43,
    "stab_pct": 0.349,
    "swing_pct": 0.651
  },
  {
    "pos": 43,
    "label": "swing",
    "start": 1878,
    "end": 1885,
    "diff": 43,
    "stab": 15,
    "swing": 29,
    "total": 44,
    "stab_pct": 0.341,
    "swing_pct": 0.659
  },
  {
    "pos": 44,
    "label": "swing",
    "start": 1922,
    "end": 1928,
    "diff": 44,
    "stab": 15,
    "swing": 30,
    "total": 45,
    "stab_pct": 0.333,
    "swing_pct": 0.667
  },
  {
    "pos": 45,
    "label": "stab",
    "start": 1961,
    "end": 1966,
    "diff": 39,
    "stab": 16,
    "swing": 30,
    "total": 46,
    "stab_pct": 0.348,
    "swing_pct": 0.652
  },
  {
    "pos": 46,
    "label": "swing",
    "start": 2004,
    "end": 2010,
    "diff": 43,
    "stab": 16,
    "swing": 31,
    "total": 47,
    "stab_pct": 0.34,
    "swing_pct": 0.66
  },
  {
    "pos": 47,
    "label": "swing",
    "start": 2048,
    "end": 2052,
    "diff": 44,
    "stab": 16,
    "swing": 32,
    "total": 48,
    "stab_pct": 0.333,
    "swing_pct": 0.667
  },
  {
    "pos": 48,
    "label": "stab",
    "start": 2087,
    "end": 2092,
    "diff": 39,
    "stab": 17,
    "swing": 32,
    "total": 49,
    "stab_pct": 0.347,
    "swing_pct": 0.653
  },
  {
    "pos": 49,
    "label": "stab",
    "start": 2126,
    "end": 2132,
    "diff": 39,
    "stab": 18,
    "swing": 32,
    "total": 50,
    "stab_pct": 0.36,
    "swing_pct": 0.64
  },
  {
    "pos": 50,
    "label": "swing",
    "start": 2170,
    "end": 2177,
    "diff": 44,
    "stab": 18,
    "swing": 33,
    "total": 51,
    "stab_pct": 0.353,
    "swing_pct": 0.647
  },
  {
    "pos": 51,
    "label": "swing",
    "start": 2213,
    "end": 2220,
    "diff": 43,
    "stab": 18,
    "swing": 34,
    "total": 52,
    "stab_pct": 0.346,
    "swing_pct": 0.654
  },
  {
    "pos": 52,
    "label": "stab",
    "start": 2252,
    "end": 2257,
    "diff": 39,
    "stab": 19,
    "swing": 34,
    "total": 53,
    "stab_pct": 0.358,
    "swing_pct": 0.642
  },
  {
    "pos": 53,
    "label": "stab",
    "start": 2292,
    "end": 2297,
    "diff": 40,
    "stab": 20,
    "swing": 34,
    "total": 54,
    "stab_pct": 0.37,
    "swing_pct": 0.63
  },
  {
    "pos": 54,
    "label": "swing",
    "start": 2335,
    "end": 2341,
    "diff": 43,
    "stab": 20,
    "swing": 35,
    "total": 55,
    "stab_pct": 0.364,
    "swing_pct": 0.636
  },
  {
    "pos": 55,
    "label": "swing",
    "start": 2378,
    "end": 2384,
    "diff": 43,
    "stab": 20,
    "swing": 36,
    "total": 56,
    "stab_pct": 0.357,
    "swing_pct": 0.643
  },
  {
    "pos": 56,
    "label": "stab",
    "start": 2420,
    "end": 2425,
    "diff": 42,
    "stab": 21,
    "swing": 36,
    "total": 57,
    "stab_pct": 0.368,
    "swing_pct": 0.632
  },
  {
    "pos": 57,
    "label": "swing",
    "start": 2463,
    "end": 2470,
    "diff": 43,
    "stab": 21,
    "swing": 37,
    "total": 58,
    "stab_pct": 0.362,
    "swing_pct": 0.638
  },
  {
    "pos": 58,
    "label": "swing",
    "start": 2506,
    "end": 2512,
    "diff": 43,
    "stab": 21,
    "swing": 38,
    "total": 59,
    "stab_pct": 0.356,
    "swing_pct": 0.644
  },
  {
    "pos": 59,
    "label": "swing",
    "start": 2550,
    "end": 2557,
    "diff": 44,
    "stab": 21,
    "swing": 39,
    "total": 60,
    "stab_pct": 0.35,
    "swing_pct": 0.65
  },
  {
    "pos": 60,
    "label": "swing",
    "start": 2593,
    "end": 2599,
    "diff": 43,
    "stab": 21,
    "swing": 40,
    "total": 61,
    "stab_pct": 0.344,
    "swing_pct": 0.656
  },
  {
    "pos": 61,
    "label": "stab",
    "start": 2634,
    "end": 2639,
    "diff": 41,
    "stab": 22,
    "swing": 40,
    "total": 62,
    "stab_pct": 0.355,
    "swing_pct": 0.645
  },
  {
    "pos": 62,
    "label": "swing",
    "start": 2679,
    "end": 2685,
    "diff": 45,
    "stab": 22,
    "swing": 41,
    "total": 63,
    "stab_pct": 0.349,
    "swing_pct": 0.651
  },
  {
    "pos": 63,
    "label": "swing",
    "start": 2722,
    "end": 2729,
    "diff": 43,
    "stab": 22,
    "swing": 42,
    "total": 64,
    "stab_pct": 0.344,
    "swing_pct": 0.656
  },
  {
    "pos": 64,
    "label": "swing",
    "start": 2765,
    "end": 2771,
    "diff": 43,
    "stab": 22,
    "swing": 43,
    "total": 65,
    "stab_pct": 0.338,
    "swing_pct": 0.662
  },
  {
    "pos": 65,
    "label": "stab",
    "start": 2805,
    "end": 2810,
    "diff": 40,
    "stab": 23,
    "swing": 43,
    "total": 66,
    "stab_pct": 0.348,
    "swing_pct": 0.652
  },
  {
    "pos": 66,
    "label": "swing",
    "start": 2848,
    "end": 2854,
    "diff": 43,
    "stab": 23,
    "swing": 44,
    "total": 67,
    "stab_pct": 0.343,
    "swing_pct": 0.657
  },
  {
    "pos": 67,
    "label": "swing",
    "start": 2892,
    "end": 2898,
    "diff": 44,
    "stab": 23,
    "swing": 45,
    "total": 68,
    "stab_pct": 0.338,
    "swing_pct": 0.662
  },
  {
    "pos": 68,
    "label": "stab",
    "start": 2931,
    "end": 2936,
    "diff": 39,
    "stab": 24,
    "swing": 45,
    "total": 69,
    "stab_pct": 0.348,
    "swing_pct": 0.652
  },
  {
    "pos": 69,
    "label": "swing",
    "start": 2974,
    "end": 2980,
    "diff": 43,
    "stab": 24,
    "swing": 46,
    "total": 70,
    "stab_pct": 0.343,
    "swing_pct": 0.657
  },
  {
    "pos": 70,
    "label": "swing",
    "start": 3018,
    "end": 3023,
    "diff": 44,
    "stab": 24,
    "swing": 47,
    "total": 71,
    "stab_pct": 0.338,
    "swing_pct": 0.662
  },
  {
    "pos": 71,
    "label": "stab",
    "start": 3059,
    "end": 3066,
    "diff": 41,
    "stab": 25,
    "swing": 47,
    "total": 72,
    "stab_pct": 0.347,
    "swing_pct": 0.653
  },
  {
    "pos": 72,
    "label": "swing",
    "start": 3102,
    "end": 3108,
    "diff": 43,
    "stab": 25,
    "swing": 48,
    "total": 73,
    "stab_pct": 0.342,
    "swing_pct": 0.658
  },
  {
    "pos": 73,
    "label": "swing",
    "start": 3145,
    "end": 3151,
    "diff": 43,
    "stab": 25,
    "swing": 49,
    "total": 74,
    "stab_pct": 0.338,
    "swing_pct": 0.662
  },
  {
    "pos": 74,
    "label": "swing",
    "start": 3188,
    "end": 3194,
    "diff": 43,
    "stab": 25,
    "swing": 50,
    "total": 75,
    "stab_pct": 0.333,
    "swing_pct": 0.667
  },
  {
    "pos": 75,
    "label": "stab",
    "start": 3229,
    "end": 3233,
    "diff": 41,
    "stab": 26,
    "swing": 50,
    "total": 76,
    "stab_pct": 0.342,
    "swing_pct": 0.658
  },
  {
    "pos": 76,
    "label": "stab",
    "start": 3268,
    "end": 3272,
    "diff": 39,
    "stab": 27,
    "swing": 50,
    "total": 77,
    "stab_pct": 0.351,
    "swing_pct": 0.649
  },
  {
    "pos": 77,
    "label": "swing",
    "start": 3313,
    "end": 3319,
    "diff": 45,
    "stab": 27,
    "swing": 51,
    "total": 78,
    "stab_pct": 0.346,
    "swing_pct": 0.654
  },
  {
    "pos": 78,
    "label": "swing",
    "start": 3356,
    "end": 3362,
    "diff": 43,
    "stab": 27,
    "swing": 52,
    "total": 79,
    "stab_pct": 0.342,
    "swing_pct": 0.658
  },
  {
    "pos": 79,
    "label": "stab",
    "start": 3396,
    "end": 3401,
    "diff": 40,
    "stab": 28,
    "swing": 52,
    "total": 80,
    "stab_pct": 0.35,
    "swing_pct": 0.65
  },
  {
    "pos": 80,
    "label": "swing",
    "start": 3439,
    "end": 3443,
    "diff": 43,
    "stab": 28,
    "swing": 53,
    "total": 81,
    "stab_pct": 0.346,
    "swing_pct": 0.654
  },
  {
    "pos": 81,
    "label": "swing",
    "start": 3482,
    "end": 3487,
    "diff": 43,
    "stab": 28,
    "swing": 54,
    "total": 82,
    "stab_pct": 0.341,
    "swing_pct": 0.659
  },
  {
    "pos": 82,
    "label": "swing",
    "start": 3525,
    "end": 3531,
    "diff": 43,
    "stab": 28,
    "swing": 55,
    "total": 83,
    "stab_pct": 0.337,
    "swing_pct": 0.663
  },
  {
    "pos": 83,
    "label": "swing",
    "start": 3568,
    "end": 3574,
    "diff": 43,
    "stab": 28,
    "swing": 56,
    "total": 84,
    "stab_pct": 0.333,
    "swing_pct": 0.667
  },
  {
    "pos": 84,
    "label": "swing",
    "start": 3611,
    "end": 3618,
    "diff": 43,
    "stab": 28,
    "swing": 57,
    "total": 85,
    "stab_pct": 0.329,
    "swing_pct": 0.671
  },
  {
    "pos": 85,
    "label": "stab",
    "start": 3651,
    "end": 3656,
    "diff": 40,
    "stab": 29,
    "swing": 57,
    "total": 86,
    "stab_pct": 0.337,
    "swing_pct": 0.663
  },
  {
    "pos": 86,
    "label": "swing",
    "start": 3695,
    "end": 3701,
    "diff": 44,
    "stab": 29,
    "swing": 58,
    "total": 87,
    "stab_pct": 0.333,
    "swing_pct": 0.667
  },
  {
    "pos": 87,
    "label": "stab",
    "start": 3736,
    "end": 3741,
    "diff": 41,
    "stab": 30,
    "swing": 58,
    "total": 88,
    "stab_pct": 0.341,
    "swing_pct": 0.659
  },
  {
    "pos": 88,
    "label": "swing",
    "start": 3779,
    "end": 3785,
    "diff": 43,
    "stab": 30,
    "swing": 59,
    "total": 89,
    "stab_pct": 0.337,
    "swing_pct": 0.663
  },
  {
    "pos": 89,
    "label": "swing",
    "start": 3822,
    "end": 3829,
    "diff": 43,
    "stab": 30,
    "swing": 60,
    "total": 90,
    "stab_pct": 0.333,
    "swing_pct": 0.667
  },
  {
    "pos": 90,
    "label": "stab",
    "start": 3862,
    "end": 3868,
    "diff": 40,
    "stab": 31,
    "swing": 60,
    "total": 91,
    "stab_pct": 0.341,
    "swing_pct": 0.659
  },
  {
    "pos": 91,
    "label": "stab",
    "start": 3904,
    "end": 3908,
    "diff": 42,
    "stab": 32,
    "swing": 60,
    "total": 92,
    "stab_pct": 0.348,
    "swing_pct": 0.652
  },
  {
    "pos": 92,
    "label": "swing",
    "start": 3948,
    "end": 3954,
    "diff": 44,
    "stab": 32,
    "swing": 61,
    "total": 93,
    "stab_pct": 0.344,
    "swing_pct": 0.656
  },
  {
    "pos": 93,
    "label": "swing",
    "start": 3992,
    "end": 3998,
    "diff": 44,
    "stab": 32,
    "swing": 62,
    "total": 94,
    "stab_pct": 0.34,
    "swing_pct": 0.66
  },
  {
    "pos": 94,
    "label": "stab",
    "start": 4031,
    "end": 4036,
    "diff": 39,
    "stab": 33,
    "swing": 62,
    "total": 95,
    "stab_pct": 0.347,
    "swing_pct": 0.653
  },
  {
    "pos": 95,
    "label": "stab",
    "start": 4071,
    "end": 4075,
    "diff": 40,
    "stab": 34,
    "swing": 62,
    "total": 96,
    "stab_pct": 0.354,
    "swing_pct": 0.646
  },
  {
    "pos": 96,
    "label": "swing",
    "start": 4114,
    "end": 4120,
    "diff": 43,
    "stab": 34,
    "swing": 63,
    "total": 97,
    "stab_pct": 0.351,
    "swing_pct": 0.649
  },
  {
    "pos": 97,
    "label": "swing",
    "start": 4157,
    "end": 4163,
    "diff": 43,
    "stab": 34,
    "swing": 64,
    "total": 98,
    "stab_pct": 0.347,
    "swing_pct": 0.653
  },
  {
    "pos": 98,
    "label": "swing",
    "start": 4200,
    "end": 4205,
    "diff": 43,
    "stab": 34,
    "swing": 65,
    "total": 99,
    "stab_pct": 0.343,
    "swing_pct": 0.657
  },
  {
    "pos": 99,
    "label": "swing",
    "start": 4243,
    "end": 4250,
    "diff": 43,
    "stab": 34,
    "swing": 66,
    "total": 100,
    "stab_pct": 0.34,
    "swing_pct": 0.66
  },
  {
    "pos": 100,
    "label": "stab",
    "start": 4283,
    "end": 4288,
    "diff": 40,
    "stab": 35,
    "swing": 66,
    "total": 101,
    "stab_pct": 0.347,
    "swing_pct": 0.653
  }
]